ai4_cli/__init__.py
ai4_cli/cli/__init__.py
ai4_cli/cli/modules.py
ai4_cli/cli/tools.py
ai4_cli/client/__init__.py
ai4_cli/client/client.py
ai4_cli/client/modules.py
ai4_cli/client/tools.py
ai4_cli/exceptions.py
ai4_cli/tests/__init__.py
ai4_cli/tests/test_cli.py
ai4_cli/tests/test_client.py
ai4_cli/utils.py
ai4_cli-0.1.0.dist-info/LICENSE
ai4_cli-0.1.0.dist-info/METADATA
ai4_cli-0.1.0.dist-info/WHEEL
ai4_cli-0.1.0.dist-info/entry_points.txt
ai4_cli-0.1.0.dist-info/RECORD
