Metadata-Version: 2.1
Name: ai4-cli
Version: 0.1.0
Summary: AI4 CLI tools and API library
Home-page: https://github.com/ai4os/ai4-cli
License: GPL-3
Author: Alvaro Lopez Garcia
Author-email: aloga@ifca.unican.es
Requires-Python: >=3.10,<4.0
Classifier: Development Status :: 5 - Production/Stable
Classifier: Environment :: Console
Classifier: Intended Audience :: Developers
Classifier: License :: OSI Approved :: Apache Software License
Classifier: License :: Other/Proprietary License
Classifier: Programming Language :: Python :: 3
Classifier: Programming Language :: Python :: 3.10
Classifier: Programming Language :: Python :: 3.11
Classifier: Programming Language :: Python :: 3.12
Classifier: Topic :: Scientific/Engineering :: Artificial Intelligence
Classifier: Topic :: Software Development :: Libraries :: Python Modules
Requires-Dist: python-dotenv (>=1.0.1,<2.0.0)
Requires-Dist: requests (>=2.32.3,<3.0.0)
Requires-Dist: typer (>=0.12.5,<0.13.0)
Project-URL: Bug Tracker, https://github.com/ai4os/ai4-clie/issues
Project-URL: Repository, https://github.com/ai4os/ai4-cli
